ReadFile/design.sv
// Code your design here
//reads data from a file ("text.txt") and stores it in a memory array

module readfile(in,out,clk);
  
  input[31:0]in;
  output reg[31:0]out;
  input clk;
  integer i;
  
  reg [31:0] memory [0:9]; //A 10-element memory array, where each element is a 32-bit register
  
  initial $readmemh("data.txt", memory);  //reads data from the file "text.txt" and initialize the memory array with the contents of the file
  
  reg[4:0]index = 5'b0000; //A 5-bit register used as an index to access the memory array
  
  initial
    begin
      for(i=0; i<9; i = i+1)
        $display("%h",i, memory[i]); //?
    end
      
  always @(posedge clk)
    begin
      out = memory[index]; //the value of "out" is assigned to the memory element indexed by "index"
      index = index + 1; //"index" is then incremented by 1, ensuring that the next memory element will be accessed in the subsequent clock cycle
    end 
endmodule

ReadFile/testbench.sv
// Code your testbench here
// or browse Examples

module readfile_tb;
  
  reg [31:0]in;
  reg clk;
  wire[31:0]out;
  
  readfile dut(.clk(clk),.in(in),.out(out));
  
  initial clk = 1'b0;
  always #10 clk = ~clk;
  
  initial
    begin
      $dumpfile("dump.vcd");
      $dumpvars;
    end
  
  initial 
    begin
      #200 $finish;  
    end
endmodule

ReadFile/dump.vcd
$date
	Fri Jun 30 06:34:40 2023
$end
$version
	Icarus Verilog
$end
$timescale
	1s
$end
$scope module readfile_tb $end
$var wire 32 ! out [31:0] $end
$var reg 1 " clk $end
$var reg 32 # in [31:0] $end
$scope module dut $end
$var wire 1 " clk $end
$var wire 32 $ in [31:0] $end
$var reg 5 % index [4:0] $end
$var reg 32 & out [31:0] $end
$var integer 32 ' i [31:0] $end
$upscope $end
$upscope $end
$enddefinitions $end
#0
$dumpvars
b1001 '
bx &
b0 %
bx $
bx #
0"
bx !
$end
#10
b1 %
b10100 !
b10100 &
1"
#20
0"
#30
b10 %
b10010 !
b10010 &
1"
#40
0"
#50
b11 %
b1001000111 !
b1001000111 &
1"
#60
0"
#70
b100 %
b101 !
b101 &
1"
#80
0"
#90
b101 %
b10010110 !
b10010110 &
1"
#100
0"
#110
b110 %
b1000011 !
b1000011 &
1"
#120
0"
#130
b111 %
b1110001 !
b1110001 &
1"
#140
0"
#150
b1000 %
b11000001000 !
b11000001000 &
1"
#160
0"
#170
b1001 %
b10001001 !
b10001001 &
1"
#180
0"
#190
b1010 %
b1100 !
b1100 &
1"
