SIPO/design.sv
// Code your design here

module SIPO(clk,si,q);
  input clk;
  input si;
  output reg [3:0]q = 0;
  always @(posedge clk)
    begin
      q[3] <= si;
      q[2] <= q[3];
      q[1] <= q[2];
      q[0] <= q[1];
    end
endmodule

SIPO/testbench.sv
// Code your testbench here
// or browse Examples

module SIPO_tb;
  
  //inputs
  reg clk,si;
  //outputs
  wire [3:0]q;
  
  SIPO dut(.clk(clk),.si(si),.q(q));
  
  initial
    begin
      clk = 0;
      si = 1;
      #10
      si = 0;
      #10
      si = 0;
      #10
      si = 1;
    end
  
  always #5 clk =~ clk;
  
  initial
    begin
      $dumpfile("dump.vcd");
      $dumpvars();
      #300
      $finish(1);
    end
endmodule

SIPO/dump.vcd
$date
	Tue Jun 27 21:55:26 2023
$end
$version
	Icarus Verilog
$end
$timescale
	1s
$end
$scope module SIPO_tb $end
$var wire 4 ! q [3:0] $end
$var reg 1 " clk $end
$var reg 1 # si $end
$scope module dut $end
$var wire 1 " clk $end
$var wire 1 # si $end
$var reg 4 $ q [3:0] $end
$upscope $end
$upscope $end
$enddefinitions $end
#0
$dumpvars
b0 $
1#
0"
b0 !
$end
#5
b1000 !
b1000 $
1"
#10
0"
0#
#15
b100 !
b100 $
1"
#20
0"
#25
b10 !
b10 $
1"
#30
0"
1#
#35
b1001 !
b1001 $
1"
#40
0"
#45
b1100 !
b1100 $
1"
#50
0"
#55
b1110 !
b1110 $
1"
#60
0"
#65
b1111 !
b1111 $
1"
